{"name":"Admin user is logged in and adds new meal category with Name testCategory","id":"user-with-role-admin-is-logged-in-and-manipulates-with-meal-categories;admin-user-is-logged-in-and-adds-new-meal-category-with-name-testcategory","testSteps":[{"number":1,"description":"Given Admin user, ROLE_ADMIN, tries to login","duration":2597,"startTime":"2021-09-15T20:43:01.480780+02:00[Europe/Skopje]","screenshots":[{"screenshot":"1458c8bd6ff1910cdc7962f95c4c917dfcd196c61f78b2fb8dd4fc8926a7e46a.png","timeStamp":1631731384078}],"result":"SUCCESS","precondition":false,"level":0,"children":[{"number":2,"description":"Admin opens the login page","duration":1927,"startTime":"2021-09-15T20:43:01.496183+02:00[Europe/Skopje]","result":"SUCCESS","precondition":false,"level":1,"children":[{"number":3,"description":"Admin opens the Login page","duration":1926,"startTime":"2021-09-15T20:43:01.496183+02:00[Europe/Skopje]","result":"SUCCESS","precondition":false,"level":2}]},{"number":4,"description":"Admin attempts login","duration":312,"startTime":"2021-09-15T20:43:03.425629400+02:00[Europe/Skopje]","result":"SUCCESS","precondition":false,"level":1,"children":[{"number":5,"description":"Admin enters \u0027admin@admin.com\u0027 into username field","duration":137,"startTime":"2021-09-15T20:43:03.426627100+02:00[Europe/Skopje]","result":"SUCCESS","precondition":false,"level":2},{"number":6,"description":"Admin enters \u0027P@ssword\u0027 into password field","duration":112,"startTime":"2021-09-15T20:43:03.564149500+02:00[Europe/Skopje]","result":"SUCCESS","precondition":false,"level":2},{"number":7,"description":"Admin clicks on login button","duration":59,"startTime":"2021-09-15T20:43:03.676239100+02:00[Europe/Skopje]","result":"SUCCESS","precondition":false,"level":2}]},{"number":8,"description":"Admin should see header profile button that is displayed","duration":234,"startTime":"2021-09-15T20:43:03.739875800+02:00[Europe/Skopje]","result":"SUCCESS","precondition":false,"level":1}]},{"number":9,"description":"And Admin user is on add new meal category page","duration":225,"startTime":"2021-09-15T20:43:04.078162200+02:00[Europe/Skopje]","result":"SUCCESS","precondition":false,"level":0,"children":[{"number":10,"description":"Admin opens meal categories page","duration":225,"startTime":"2021-09-15T20:43:04.078162200+02:00[Europe/Skopje]","result":"SUCCESS","precondition":false,"level":1,"children":[{"number":11,"description":"Admin opens the Meal categories add page","duration":224,"startTime":"2021-09-15T20:43:04.078162200+02:00[Europe/Skopje]","result":"SUCCESS","precondition":false,"level":2}]}]},{"number":12,"description":"When Admin user enters \"testCategory\" and \"https://www.fitfatherproject.com/wp-content/uploads/2017/09/meal-prep-400.jpg\" for meal category","duration":2351,"startTime":"2021-09-15T20:43:04.304306300+02:00[Europe/Skopje]","result":"SUCCESS","precondition":false,"level":0,"children":[{"number":13,"description":"Admin attempts to add new meal category","duration":346,"startTime":"2021-09-15T20:43:04.306306600+02:00[Europe/Skopje]","result":"SUCCESS","precondition":false,"level":1,"children":[{"number":14,"description":"Admin enters \u0027testCategory\u0027 into meal category name field","duration":117,"startTime":"2021-09-15T20:43:04.306306600+02:00[Europe/Skopje]","result":"SUCCESS","precondition":false,"level":2},{"number":15,"description":"Admin enters \u0027https://www.fitfatherproject.com/wp-content/uploads/2017/09/meal-prep-400.jpg\u0027 then hits [ENTER] into meal category imageUrl field","duration":227,"startTime":"2021-09-15T20:43:04.424255300+02:00[Europe/Skopje]","result":"SUCCESS","precondition":false,"level":2}]}]},{"number":16,"description":"Then Admin user should see table with meal categories with 12 rows","duration":15,"startTime":"2021-09-15T20:43:06.656263100+02:00[Europe/Skopje]","result":"SUCCESS","precondition":false,"level":0,"children":[{"number":17,"description":"Admin should see a collection of web elements located by .mealCategoriesRow that is of size: \u003c12\u003e","duration":15,"startTime":"2021-09-15T20:43:06.656263100+02:00[Europe/Skopje]","result":"SUCCESS","precondition":false,"level":1}]}],"userStory":{"id":"user-with-role-admin-is-logged-in-and-manipulates-with-meal-categories","storyName":"User with role admin is logged in and manipulates with meal categories","path":"mealCategories/003mealCategories.feature","type":"feature"},"featureTag":{"name":"Meal categories/User with role admin is logged in and manipulates with meal categories","type":"feature","displayName":"Meal categories/User with role admin is logged in and manipulates with meal categories"},"title":"Admin user is logged in and adds new meal category with Name testCategory","description":"  and imageUrl https://www.fitfatherproject.com/wp-content/uploads/2017/09/meal-prep-400.jpg","tags":[{"name":"Meal categories","type":"capability","displayName":"Meal categories"},{"name":"Meal categories/User with role admin is logged in and manipulates with meal categories","type":"feature","displayName":"User with role admin is logged in and manipulates with meal categories"}],"startTime":"2021-09-15T20:43:01.480780+02:00[Europe/Skopje]","duration":5190,"projectKey":"","sessionId":"fbd518ea3b8eae37141e422cadc83804","driver":"chrome:admin","isManualTestingUpToDate":false,"manual":false,"testSource":"Cucumber","actors":[{"name":"Admin","can":["browse the web"]}],"result":"SUCCESS"}